doubleclickcrypto/__init__.py
doubleclickcrypto/doubleclickcrypto.py
doubleclickcrypto-0.1.1.dist-info/LICENSE
doubleclickcrypto-0.1.1.dist-info/METADATA
doubleclickcrypto-0.1.1.dist-info/WHEEL
doubleclickcrypto-0.1.1.dist-info/top_level.txt
doubleclickcrypto-0.1.1.dist-info/RECORD
