Metadata-Version: 2.1
Name: doubleclickcrypto
Version: 0.1.1
Summary: Module for decrypting doubleclick price confirmations
Home-page: https://github.com/danielhedren/doubleclickcrypto
Author: Daniel Hedrén
Author-email: danielhedren@gmail.com
License: UNKNOWN
Keywords: google doubleclick hmac price confirmation winning bid decryption decrypt real time bidding rtb
Platform: UNKNOWN
Classifier: Programming Language :: Python :: 3
Classifier: License :: OSI Approved :: MIT License
Classifier: Operating System :: OS Independent
Requires-Python: >=3.6
